space/__init__.py
space/catalogs/__init__.py
space/catalogs/base.py
space/catalogs/directory.py
space/core/__init__.py
space/core/datasets.py
space/core/jobs.py
space/core/options.py
space/core/random_access.py
space/core/runners.py
space/core/storage.py
space/core/views.py
space/core/fs/__init__.py
space/core/fs/array_record.py
space/core/fs/arrow.py
space/core/fs/base.py
space/core/fs/factory.py
space/core/fs/parquet.py
space/core/loaders/__init__.py
space/core/loaders/array_record.py
space/core/loaders/parquet.py
space/core/manifests/__init__.py
space/core/manifests/falsifiable_filters.py
space/core/manifests/index.py
space/core/manifests/record.py
space/core/ops/__init__.py
space/core/ops/append.py
space/core/ops/base.py
space/core/ops/change_data.py
space/core/ops/delete.py
space/core/ops/insert.py
space/core/ops/read.py
space/core/ops/utils.py
space/core/proto/__init__.py
space/core/proto/metadata_pb2.py
space/core/proto/metadata_pb2.pyi
space/core/proto/runtime_pb2.py
space/core/proto/runtime_pb2.pyi
space/core/schema/__init__.py
space/core/schema/arrow.py
space/core/schema/constants.py
space/core/schema/field_ids.py
space/core/schema/substrait.py
space/core/schema/utils.py
space/core/schema/types/__init__.py
space/core/schema/types/files.py
space/core/schema/types/tf_features.py
space/core/serializers/__init__.py
space/core/serializers/base.py
space/core/transform/__init__.py
space/core/transform/join.py
space/core/transform/plans.py
space/core/transform/udfs.py
space/core/transform/utils.py
space/core/utils/__init__.py
space/core/utils/constants.py
space/core/utils/errors.py
space/core/utils/lazy_imports_utils.py
space/core/utils/paths.py
space/core/utils/protos.py
space/core/utils/uuids.py
space/ray/__init__.py
space/ray/data_sources.py
space/ray/options.py
space/ray/runners.py
space/ray/ops/__init__.py
space/ray/ops/append.py
space/ray/ops/change_data.py
space/ray/ops/delete.py
space/ray/ops/insert.py
space/ray/ops/join.py
space/ray/ops/utils.py
space_datasets-0.0.11.dist-info/METADATA
space_datasets-0.0.11.dist-info/WHEEL
space_datasets-0.0.11.dist-info/top_level.txt
space_datasets-0.0.11.dist-info/RECORD
